{
  "SiteElement": [
    {
      "name": "Luxel",
      "sectorsNumber": 2,
      "groupsNumber": 4,
      "devicesNumber": 16,
      "status": "unprovision",
      "SectorElement": 
      [
        {
          "name": "s0001",
          "groupsNumber": 2,
          "devicesNumber": 8,
          "status": "unprovision",
          "GroupElement": 
          [
            {
              "name": "g0001",
              "devicesNumber": 4,
              "status": "unprovision",
              "DeviceElement": 
              [
                {
                  "name": "DCIBMM",
                  "number": 1,
                  "id": "123456789",
                  "status": "unscanned"
                },
                {
                  "name": "SMM30",
                  "number": 2,
                   "id": "123456789",
                  "status": "unscanned"
                },
                {
                  "name": "SMM30",
                  "number": 3,
                  "id": "123456789",
                  "status": "unscanned"
                },
                {
                  "name": "SMM30",
                  "number": 4,
                  "id": "123456789",
                  "status": "unscanned"
                }
              ]
            },
            {
              "name": "g0002",
              "devicesNumber": 4,
              "status": "unprovision"
              "DeviceElement": 
              [
                {
                  "name": "DCIBMM",
                  "number": 1,
                  "id": "123456789",
                  "status": "unscanned"
                },
                {
                  "name": "SMM30",
                  "number": 2,
                  "id": "123456789",
                  "status": "unscanned"
                },
                {
                  "name": "SMM30",
                  "number": 3,
                  "id": "123456789",
                  "status": "unscanned"
                },
                {
                  "name": "SMM30",
                  "number": 4,
                  "id": "123456789",
                  "status": "unscanned"
                }
              ]
            }
          ]
        },
        {
          "name": "s0001",
          "groupsNumber": 2,
          "devicesNumber": 8,
          "status": "unprovision",
          "GroupElement": 
          [
            {
              "name": "g0003",
              "devicesNumber": 4,
              "status": "unprovision",
              "DeviceElement": 
              [
                {
                  "name": "DCIBMM",
                  "number": 1,
                  "id": "123456789",
                  "status": "unscanned"
                },
                {
                  "name": "SMM30",
                  "number": 2,
                  "id": "123456789",
                  "status": "unscanned"
                },
                {
                  "name": "SMM30",
                  "number": 3,
                  "id": "123456789",
                  "status": "unscanned"
                },
                {
                  "name": "SMM30",
                  "number": 4,
                  "id": "123456789",
                  "status": "unscanned"
                }
              ]
            },
            {
              "name": "g0004",
              "devicesNumber": 4,
              "status": "unprovision",
              "DeviceElement": 
              [
                {
                  "name": "DCIBMM",
                  "number": 1,
                  "id": "123456789",
                  "status": "unscanned"
                },
                {
                  "name": "SMM30",
                  "number": 2,
                  "id": "123456789",
                  "status": "unscanned"
                },
                {
                  "name": "SMM30",
                  "number": 3,
                  "id": "123456789",
                  "status": "unscanned"
                },
                {
                  "name": "SMM30",
                  "number": 4,
                  "id": "123",
                  "status": "unscanned"
                }
              ]
            }
          ]
        }
      ]
    },
    {
      "name": "Ivan`s solarfarm",
      "sectorsNumber": 2,
      "groupsNumber": 4,
      "devicesNumber": 16,
      "status": "unprovision",
      "SectorElement": 
      [
        {
          "name": "s0001",
          "groupsNumber": 2,
          "devicesNumber": 8,
          "status": "unprovision",
          "GroupElement": 
          [
            {
              "name": "g0001",
              "devicesNumber": 4,
              "status": "unprovision",
              "DeviceElement": 
              [
                {
                  "name": "DCIBMM",
                  "number": 1,
                  "id": "123456789",
                  "status": "unscanned"
                },
                {
                  "name": "SMM30",
                  "number": 2,
                  "id": "123456789",
                  "status": "unscanned"
                },
                {
                  "name": "SMM30",
                  "number": 3,
                  "id": "123456789",
                  "status": "unscanned"
                },
                {
                  "name": "SMM30",
                  "number": 4,
                  "id": "123456789",
                  "status": "unscanned"
                }
              ]
            },
            {
              "name": "g0002",
              "devicesNumber": 4,
              "status": "unprovision"
              "DeviceElement": 
              [
                {
                  "name": "DCIBMM",
                  "number": 1,
                  "id": "123456789",
                  "status": "unscanned"
                },
                {
                  "name": "SMM30",
                  "number": 2,
                  "id": "123456789",
                  "status": "unscanned"
                },
                {
                  "name": "SMM30",
                  "number": 3,
                  "id": "123456789",
                  "status": "unscanned"
                },
                {
                  "name": "SMM30",
                  "number": 4,
                  "id": "123456789",
                  "status": "unscanned"
                }
              ]
            }
          ]
        },
        {
          "name": "s0001",
          "groupsNumber": 2,
          "devicesNumber": 8,
          "status": "unprovision",
          "GroupElement": 
          [
            {
              "name": "g0003",
              "devicesNumber": 4,
              "status": "unprovision",
              "DeviceElement": 
              [
                {
                  "name": "DCIBMM",
                  "number": 1,
                  "id": "123456789",
                  "status": "unscanned"
                },
                {
                  "name": "SMM30",
                  "number": 2,
                  "id": "123456789",
                  "status": "unscanned"
                },
                {
                  "name": "SMM30",
                  "number": 3,
                  "id": "123456789",
                  "status": "unscanned"
                },
                {
                  "name": "SMM30",
                  "number": 4,
                  "id": "123456789",
                  "status": "unscanned"
                }
              ]
            },
            {
              "name": "g0004",
              "devicesNumber": 4,
              "status": "unprovision"
              "DeviceElement": 
              [
                {
                  "name": "DCIBMM",
                  "number": 1,
                  "id": "123456789",
                  "status": "unscanned"
                },
                {
                  "name": "SMM30",
                  "number": 2,
                  "id": "123456789",
                  "status": "unscanned"
                },
                {
                  "name": "SMM30",
                  "number": 3,
                  "id": "123456789",
                  "status": "unscanned"
                },
                {
                  "name": "SMM30",
                  "number": 4,
                  "id": "123",
                  "status": "unscanned"
                }
              ]
            }
          ]
        }
      ]
    }
  ]
}